ehttp/__init__.py
ehttp/classes.py
ehttp/constants.py
ehttp/exceptions.py
ehttp/file_manager.py
ehttp/proxy.py
ehttp/server.py
ehttp/utils.py
ehttp-0.1.7.2.dist-info/METADATA
ehttp-0.1.7.2.dist-info/WHEEL
ehttp-0.1.7.2.dist-info/top_level.txt
ehttp-0.1.7.2.dist-info/RECORD
