Metadata-Version: 2.1
Name: ehttp
Version: 0.1.7.2
Summary: Tool for easy creating http api
Home-page: https://gitlab.com/cuciki/ehttp
Author: Andrey Shcarev
Author-email: wex335@yandex.ru
License: MIT
Download-URL: https://pypi.org/project/ehttp/
Keywords: http,ehttp,easyhttp
Platform: UNKNOWN
